{"producto": "PLACAS", "modelo": "BARILOCHE", "ancho": "1.20", "alto": "2.40", "tipo": "Estándar", "placas_por_metro": 7, "stock": 0, "costo": 50000, "porcentaje_ganancia": 100, "porcentaje_tarjeta": 15, "total_redondeo": 1},
{"producto": "PLACAS", "modelo": "BURBUJA", "ancho": "1.20", "alto": "2.40", "tipo": "Estándar", "placas_por_metro": 6,3, "stock": 0, "costo": 125000, "porcentaje_ganancia": 100, "porcentaje_tarjeta": 15, "total_redondeo": 1},
{"producto": "PLACAS", "modelo": "DISEÑO", "ancho": "1.20", "alto": "2.40", "tipo": "Estándar", "placas_por_metro": 4, "stock": 0, "costo": 425000, "porcentaje_ganancia": 100, "porcentaje_tarjeta": 15, "total_redondeo": 1},
{"producto": "PLACAS", "modelo": "FLOR", "ancho": "1.20", "alto": "2.40", "tipo": "Estándar", "placas_por_metro": 6,3, "stock": 0, "costo": 750000, "porcentaje_ganancia": 100, "porcentaje_tarjeta": 15, "total_redondeo": 1},
{"producto": "PLACAS", "modelo": "LADRILLO", "ancho": "1.20", "alto": "2.40", "tipo": "Estándar", "placas_por_metro": 3, "stock": 0, "costo": null, "porcentaje_ganancia": 100, "porcentaje_tarjeta": 15, "total_redondeo": 1},
{"producto": "PLACAS", "modelo": "LAJA", "ancho": "1.20", "alto": "2.40", "tipo": "Estándar", "placas_por_metro": 8, "stock": 0, "costo": 750000, "porcentaje_ganancia": 100, "porcentaje_tarjeta": 15, "total_redondeo": 1},
{"producto": "PLACAS", "modelo": "LORETO", "ancho": "1.20", "alto": "2.40", "tipo": "Estándar", "placas_por_metro": 8, "stock": 0, "costo": 750000, "porcentaje_ganancia": 100, "porcentaje_tarjeta": 15, "total_redondeo": 1},
{"producto": "PLACAS", "modelo": "MAYA", "ancho": "1.20", "alto": "2.40", "tipo": "Estándar", "placas_por_metro": 7, "stock": 0, "costo": null, "porcentaje_ganancia": 100, "porcentaje_tarjeta": 15, "total_redondeo": 1},
{"producto": "PLACAS", "modelo": "MOLDURAS", "ancho": "1.20", "alto": "2.40", "tipo": "Estándar", "placas_por_metro": 2, "stock": 0, "costo": null, "porcentaje_ganancia": 100, "porcentaje_tarjeta": 15, "total_redondeo": 1},
{"producto": "PLACAS", "modelo": "ONDAS", "ancho": "1.20", "alto": "2.40", "tipo": "Estándar", "placas_por_metro": 7, "stock": 0, "costo": 500000, "porcentaje_ganancia": 100, "porcentaje_tarjeta": 15, "total_redondeo": 1},
{"producto": "PLACAS", "modelo": "PANAL", "ancho": "1.20", "alto": "2.40", "tipo": "Estándar", "placas_por_metro": 8, "stock": 0, "costo": 750000, "porcentaje_ganancia": 100, "porcentaje_tarjeta": 15, "total_redondeo": 1},
{"producto": "PLACAS", "modelo": "PIEDRA", "ancho": "1.20", "alto": "2.40", "tipo": "Estándar", "placas_por_metro": 6,7, "stock": 0, "costo": 1600000, "porcentaje_ganancia": 100, "porcentaje_tarjeta": 15, "total_redondeo": 1},
{"producto": "PLACAS", "modelo": "PIZARRA", "ancho": "1.20", "alto": "2.40", "tipo": "Estándar", "placas_por_metro": 6,5, "stock": 0, "costo": 350000, "porcentaje_ganancia": 100, "porcentaje_tarjeta": 15, "total_redondeo": 1},
{"producto": "PLACAS", "modelo": "QATAR", "ancho": "1.20", "alto": "2.40", "tipo": "Estándar", "placas_por_metro": 4, "stock": 0, "costo": null, "porcentaje_ganancia": 100, "porcentaje_tarjeta": 15, "total_redondeo": 1},
{"producto": "PLACAS", "modelo": "SOL", "ancho": "1.20", "alto": "2.40", "tipo": "Estándar", "placas_por_metro": 4, "stock": 0, "costo": 500000, "porcentaje_ganancia": 100, "porcentaje_tarjeta": 15, "total_redondeo": 1},
{"producto": "PLACAS", "modelo": "TECNO", "ancho": "1.20", "alto": "2.40", "tipo": "Estándar", "placas_por_metro": 6,3, "stock": 0, "costo": null, "porcentaje_ganancia": 100, "porcentaje_tarjeta": 15, "total_redondeo": 1},
{"producto": "PLACAS", "modelo": "TESLA", "ancho": "1.20", "alto": "2.40", "tipo": "Estándar", "placas_por_metro": 4, "stock": 0, "costo": 500000, "porcentaje_ganancia": 100, "porcentaje_tarjeta": 15, "total_redondeo": 1},
{"producto": "PLACAS", "modelo": "TRAVERTINO", "ancho": "1.20", "alto": "2.40", "tipo": "Estándar", "placas_por_metro": 7, "stock": 0, "costo": 750000, "porcentaje_ganancia": 100, "porcentaje_tarjeta": 15, "total_redondeo": 1},
{"producto": "PLACAS", "modelo": "VALENCI", "ancho": "1.20", "alto": "2.40", "tipo": "Estándar", "placas_por_metro": 4, "stock": 0, "costo": 500000, "porcentaje_ganancia": 100, "porcentaje_tarjeta": 15, "total_redondeo": 1},
{"producto": "WPC", "modelo": "CEDRO 2,7M", "ancho": "1.20", "alto": "2.40", "tipo": "Estándar", "placas_por_metro": 1, "stock": 0, "costo": 1000000, "porcentaje_ganancia": 100, "porcentaje_tarjeta": 15, "total_redondeo": 1},
{"producto": "WPC", "modelo": "CARBONO 2,7M", "ancho": "1.20", "alto": "2.40", "tipo": "Estándar", "placas_por_metro": 1, "stock": 0, "costo": 1000000, "porcentaje_ganancia": 100, "porcentaje_tarjeta": 15, "total_redondeo": 1},
{"producto": "WPC", "modelo": "MARENGO 2,9M", "ancho": "1.20", "alto": "2.40", "tipo": "Estándar", "placas_por_metro": 1, "stock": 0, "costo": null, "porcentaje_ganancia": 100, "porcentaje_tarjeta": 15, "total_redondeo": 1},
{"producto": "WPC", "modelo": "ATAKAMA 2,9M", "ancho": "1.20", "alto": "2.40", "tipo": "Estándar", "placas_por_metro": 1, "stock": 0, "costo": null, "porcentaje_ganancia": 100, "porcentaje_tarjeta": 15, "total_redondeo": 1},
{"producto": "WPC", "modelo": "ABEDUI 2,9M", "ancho": "1.20", "alto": "2.40", "tipo": "Estándar", "placas_por_metro": 1, "stock": 0, "costo": null, "porcentaje_ganancia": 100, "porcentaje_tarjeta": 15, "total_redondeo": 1},
{"producto": "WPC", "modelo": "ALTIA GRAY 2,9M", "ancho": "1.20", "alto": "2.40", "tipo": "Estándar", "placas_por_metro": 1, "stock": 0, "costo": null, "porcentaje_ganancia": 100, "porcentaje_tarjeta": 15, "total_redondeo": 1},
{"producto": "SIMIL_MARMOL", "modelo": "CALACATTA 2,4M", "ancho": "1.20", "alto": "2.40", "tipo": "Estándar", "placas_por_metro": 1, "stock": 0, "costo": null, "porcentaje_ganancia": 100, "porcentaje_tarjeta": 15, "total_redondeo": 1},
{"producto": "SIMIL_MARMOL", "modelo": "CARRARA 2,4M", "ancho": "1.20", "alto": "2.40", "tipo": "Estándar", "placas_por_metro": 1, "stock": 0, "costo": null, "porcentaje_ganancia": 100, "porcentaje_tarjeta": 15, "total_redondeo": 1},
{"producto": "SIMIL_MARMOL", "modelo": "DELUXE 2,4M", "ancho": "1.20", "alto": "2.40", "tipo": "Estándar", "placas_por_metro": 1, "stock": 0, "costo": 1500000, "porcentaje_ganancia": 100, "porcentaje_tarjeta": 15, "total_redondeo": 1},
{"producto": "SIMIL_MARMOL", "modelo": "EMPERADOR 2,4M", "ancho": "1.20", "alto": "2.40", "tipo": "Estándar", "placas_por_metro": 1, "stock": 0, "costo": null, "porcentaje_ganancia": 100, "porcentaje_tarjeta": 15, "total_redondeo": 1},
{"producto": "SIMIL_MARMOL", "modelo": "L. BEIGE 2,4M", "ancho": "1.20", "alto": "2.40", "tipo": "Estándar", "placas_por_metro": 1, "stock": 0, "costo": null, "porcentaje_ganancia": 100, "porcentaje_tarjeta": 15, "total_redondeo": 1},
{"producto": "SIMIL_MARMOL", "modelo": "MARQUINA 2,4M", "ancho": "1.20", "alto": "2.40", "tipo": "Estándar", "placas_por_metro": 1, "stock": 0, "costo": 3500000, "porcentaje_ganancia": 100, "porcentaje_tarjeta": 15, "total_redondeo": 1},
{"producto": "ZOCALOS_PVC", "modelo": "NEGRO 2,4M", "ancho": "1.20", "alto": "2.40", "tipo": "Estándar", "placas_por_metro": 1, "stock": 0, "costo": null, "porcentaje_ganancia": 100, "porcentaje_tarjeta": 15, "total_redondeo": 1},
{"producto": "ZOCALOS_PVC", "modelo": "BLANCO 2,4M", "ancho": "1.20", "alto": "2.40", "tipo": "Estándar", "placas_por_metro": 1, "stock": 0, "costo": 500000, "porcentaje_ganancia": 100, "porcentaje_tarjeta": 15, "total_redondeo": 1},
{"producto": "PVC_BLANCO", "modelo": "PVC BLANCO 2M", "ancho": "1.20", "alto": "2.40", "tipo": "Estándar", "placas_por_metro": 1, "stock": 0, "costo": 1000000, "porcentaje_ganancia": 100, "porcentaje_tarjeta": 15, "total_redondeo": 1},
{"producto": "PVC_BLANCO", "modelo": "PVC BLANCO 2,5M", "ancho": "1.20", "alto": "2.40", "tipo": "Estándar", "placas_por_metro": 1, "stock": 0, "costo": null, "porcentaje_ganancia": 100, "porcentaje_tarjeta": 15, "total_redondeo": 1},
{"producto": "PVC_BLANCO", "modelo": "PVC BLANCO 3M", "ancho": "1.20", "alto": "2.40", "tipo": "Estándar", "placas_por_metro": 1, "stock": 0, "costo": null, "porcentaje_ganancia": 100, "porcentaje_tarjeta": 15, "total_redondeo": 1},
{"producto": "PVC_BLANCO", "modelo": "PVC BLANCO 3,5M", "ancho": "1.20", "alto": "2.40", "tipo": "Estándar", "placas_por_metro": 1, "stock": 0, "costo": null, "porcentaje_ganancia": 100, "porcentaje_tarjeta": 15, "total_redondeo": 1},
{"producto": "PVC_BLANCO", "modelo": "PVC BLANCO 4M", "ancho": "1.20", "alto": "2.40", "tipo": "Estándar", "placas_por_metro": 1, "stock": 0, "costo": null, "porcentaje_ganancia": 100, "porcentaje_tarjeta": 15, "total_redondeo": 1},
{"producto": "PVC_BLANCO", "modelo": "PVC BLANCO 4,5M", "ancho": "1.20", "alto": "2.40", "tipo": "Estándar", "placas_por_metro": 1, "stock": 0, "costo": null, "porcentaje_ganancia": 100, "porcentaje_tarjeta": 15, "total_redondeo": 1},
{"producto": "PVC_BLANCO", "modelo": "PVC BLANCO 5M", "ancho": "1.20", "alto": "2.40", "tipo": "Estándar", "placas_por_metro": 1, "stock": 0, "costo": 1500000, "porcentaje_ganancia": 100, "porcentaje_tarjeta": 15, "total_redondeo": 1},
{"producto": "PVC_BLANCO", "modelo": "PVC BLANCO 5,5M", "ancho": "1.20", "alto": "2.40", "tipo": "Estándar", "placas_por_metro": 1, "stock": 0, "costo": null, "porcentaje_ganancia": 100, "porcentaje_tarjeta": 15, "total_redondeo": 1},
{"producto": "PVC_BLANCO", "modelo": "PVC BLANCO 6M", "ancho": "1.20", "alto": "2.40", "tipo": "Estándar", "placas_por_metro": 1, "stock": 0, "costo": null, "porcentaje_ganancia": 100, "porcentaje_tarjeta": 15, "total_redondeo": 1},
{"producto": "PVC_COLOR", "modelo": "PVC CEDRO 4M", "ancho": "1.20", "alto": "2.40", "tipo": "Estándar", "placas_por_metro": 1, "stock": 0, "costo": null, "porcentaje_ganancia": 100, "porcentaje_tarjeta": 15, "total_redondeo": 1},
{"producto": "PVC_COLOR", "modelo": "PVC CEDRO 5M", "ancho": "1.20", "alto": "2.40", "tipo": "Estándar", "placas_por_metro": 1, "stock": 0, "costo": null, "porcentaje_ganancia": 100, "porcentaje_tarjeta": 15, "total_redondeo": 1},
{"producto": "PVC_COLOR", "modelo": "PVC CEDRO 6M", "ancho": "1.20", "alto": "2.40", "tipo": "Estándar", "placas_por_metro": 1, "stock": 0, "costo": null, "porcentaje_ganancia": 100, "porcentaje_tarjeta": 15, "total_redondeo": 1},
{"producto": "PVC_COLOR", "modelo": "PVC CEREJEIRA 4M", "ancho": "1.20", "alto": "2.40", "tipo": "Estándar", "placas_por_metro": 1, "stock": 0, "costo": null, "porcentaje_ganancia": 100, "porcentaje_tarjeta": 15, "total_redondeo": 1},
{"producto": "PVC_COLOR", "modelo": "PVC CEREJEIRA 5M", "ancho": "1.20", "alto": "2.40", "tipo": "Estándar", "placas_por_metro": 1, "stock": 0, "costo": null, "porcentaje_ganancia": 100, "porcentaje_tarjeta": 15, "total_redondeo": 1},
{"producto": "PVC_COLOR", "modelo": "PVC CEREJEIRA 6M", "ancho": "1.20", "alto": "2.40", "tipo": "Estándar", "placas_por_metro": 1, "stock": 0, "costo": null, "porcentaje_ganancia": 100, "porcentaje_tarjeta": 15, "total_redondeo": 1},
{"producto": "PVC_COLOR", "modelo": "PVC GRIS 4M", "ancho": "1.20", "alto": "2.40", "tipo": "Estándar", "placas_por_metro": 1, "stock": 0, "costo": null, "porcentaje_ganancia": 100, "porcentaje_tarjeta": 15, "total_redondeo": 1},
{"producto": "PVC_COLOR", "modelo": "PVC GRIS 5M", "ancho": "1.20", "alto": "2.40", "tipo": "Estándar", "placas_por_metro": 1, "stock": 0, "costo": null, "porcentaje_ganancia": 100, "porcentaje_tarjeta": 15, "total_redondeo": 1},
{"producto": "PVC_COLOR", "modelo": "PVC GRIS 6M", "ancho": "1.20", "alto": "2.40", "tipo": "Estándar", "placas_por_metro": 1, "stock": 0, "costo": null, "porcentaje_ganancia": 100, "porcentaje_tarjeta": 15, "total_redondeo": 1},
{"producto": "PVC_COLOR", "modelo": "PVC GRIS PERLADO 4M", "ancho": "1.20", "alto": "2.40", "tipo": "Estándar", "placas_por_metro": 1, "stock": 0, "costo": null, "porcentaje_ganancia": 100, "porcentaje_tarjeta": 15, "total_redondeo": 1},
{"producto": "PVC_COLOR", "modelo": "PVC GRIS PERLADO 5M", "ancho": "1.20", "alto": "2.40", "tipo": "Estándar", "placas_por_metro": 1, "stock": 0, "costo": null, "porcentaje_ganancia": 100, "porcentaje_tarjeta": 15, "total_redondeo": 1},
{"producto": "PVC_COLOR", "modelo": "PVC GRIS PERLADO 6M", "ancho": "1.20", "alto": "2.40", "tipo": "Estándar", "placas_por_metro": 1, "stock": 0, "costo": null, "porcentaje_ganancia": 100, "porcentaje_tarjeta": 15, "total_redondeo": 1},
{"producto": "PVC_COLOR", "modelo": "PVC HAYA 4M", "ancho": "1.20", "alto": "2.40", "tipo": "Estándar", "placas_por_metro": 1, "stock": 0, "costo": 950000, "porcentaje_ganancia": 100, "porcentaje_tarjeta": 15, "total_redondeo": 1},
{"producto": "PVC_COLOR", "modelo": "PVC HAYA 5M", "ancho": "1.20", "alto": "2.40", "tipo": "Estándar", "placas_por_metro": 1, "stock": 0, "costo": null, "porcentaje_ganancia": 100, "porcentaje_tarjeta": 15, "total_redondeo": 1},
{"producto": "PVC_COLOR", "modelo": "PVC HAYA 6M", "ancho": "1.20", "alto": "2.40", "tipo": "Estándar", "placas_por_metro": 1, "stock": 0, "costo": null, "porcentaje_ganancia": 100, "porcentaje_tarjeta": 15, "total_redondeo": 1},
{"producto": "PVC_PERFIL", "modelo": "F BLANCO 3M", "ancho": "1.20", "alto": "2.40", "tipo": "Estándar", "placas_por_metro": 1, "stock": 0, "costo": null, "porcentaje_ganancia": 100, "porcentaje_tarjeta": 15, "total_redondeo": 1},
{"producto": "PVC_PERFIL", "modelo": "F BLANCO 4M", "ancho": "1.20", "alto": "2.40", "tipo": "Estándar", "placas_por_metro": 1, "stock": 0, "costo": null, "porcentaje_ganancia": 100, "porcentaje_tarjeta": 15, "total_redondeo": 1},
{"producto": "PVC_PERFIL", "modelo": "F BLANCO 5M", "ancho": "1.20", "alto": "2.40", "tipo": "Estándar", "placas_por_metro": 1, "stock": 0, "costo": null, "porcentaje_ganancia": 100, "porcentaje_tarjeta": 15, "total_redondeo": 1},
{"producto": "PVC_PERFIL", "modelo": "F CEDRO 4M", "ancho": "1.20", "alto": "2.40", "tipo": "Estándar", "placas_por_metro": 1, "stock": 0, "costo": null, "porcentaje_ganancia": 100, "porcentaje_tarjeta": 15, "total_redondeo": 1},
{"producto": "MATERIAL", "modelo": "Silicona neutra", "ancho": "1.20", "alto": "2.40", "tipo": "Estándar", "placas_por_metro": 1, "stock": 0, "costo": null, "porcentaje_ganancia": 100, "porcentaje_tarjeta": 15, "total_redondeo": 1},
{"producto": "MATERIAL", "modelo": "Poliubretano", "ancho": "1.20", "alto": "2.40", "tipo": "Estándar", "placas_por_metro": 1, "stock": 0, "costo": null, "porcentaje_ganancia": 100, "porcentaje_tarjeta": 15, "total_redondeo": 1},
{"producto": "MATERIAL", "modelo": "SELLA JUNTA", "ancho": "1.20", "alto": "2.40", "tipo": "Estándar", "placas_por_metro": 1, "stock": 0, "costo": null, "porcentaje_ganancia": 100, "porcentaje_tarjeta": 15, "total_redondeo": 1},
{"producto": "MATERIAL", "modelo": "PEGAMENTO", "ancho": "1.20", "alto": "2.40", "tipo": "Estándar", "placas_por_metro": 1, "stock": 0, "costo": null, "porcentaje_ganancia": 100, "porcentaje_tarjeta": 15, "total_redondeo": 1},
{"producto": "MATERIAL", "modelo": "MANGA", "ancho": "1.20", "alto": "2.40", "tipo": "Estándar", "placas_por_metro": 1, "stock": 0, "costo": null, "porcentaje_ganancia": 100, "porcentaje_tarjeta": 15, "total_redondeo": 1},
{"producto": "MATERIAL", "modelo": "Chapita Fijacion", "ancho": "1.20", "alto": "2.40", "tipo": "Estándar", "placas_por_metro": 1, "stock": 0, "costo": null, "porcentaje_ganancia": 100, "porcentaje_tarjeta": 15, "total_redondeo": 1},
{"producto": "MATERIAL", "modelo": "Poliubretano", "ancho": "1.20", "alto": "2.40", "tipo": "Estándar", "placas_por_metro": 1, "stock": 0, "costo": null, "porcentaje_ganancia": 100, "porcentaje_tarjeta": 15, "total_redondeo": 1},
{"producto": "INSTALACION", "modelo": "INSTALACION", "ancho": "1.20", "alto": "2.40", "tipo": "Estándar", "placas_por_metro": 1, "stock": 0, "costo": null, "porcentaje_ganancia": 100, "porcentaje_tarjeta": 15, "total_redondeo": 1},
{"producto": "WPC", "modelo": "CANTONERA CARBONO", "ancho": "1.20", "alto": "2.40", "tipo": "Estándar", "placas_por_metro": 1, "stock": 0, "costo": null, "porcentaje_ganancia": 100, "porcentaje_tarjeta": 15, "total_redondeo": 1},
{"producto": "WPC", "modelo": "CANTONERA MARENGO", "ancho": "1.20", "alto": "2.40", "tipo": "Estándar", "placas_por_metro": 1, "stock": 0, "costo": null, "porcentaje_ganancia": 100, "porcentaje_tarjeta": 15, "total_redondeo": 1},
{"producto": "WPC", "modelo": "CANTONERA ALTIA", "ancho": "1.20", "alto": "2.40", "tipo": "Estándar", "placas_por_metro": 1, "stock": 0, "costo": null, "porcentaje_ganancia": 100, "porcentaje_tarjeta": 15, "total_redondeo": 1},
{"producto": "TELGOPOR", "modelo": "TELGO 35mm", "ancho": "1.20", "alto": "2.40", "tipo": "Estándar", "placas_por_metro": 1, "stock": 0, "costo": null, "porcentaje_ganancia": 100, "porcentaje_tarjeta": 15, "total_redondeo": 1},
{"producto": "TELGOPOR", "modelo": "TELGO 40mm", "ancho": "1.20", "alto": "2.40", "tipo": "Estándar", "placas_por_metro": 1, "stock": 0, "costo": null, "porcentaje_ganancia": 100, "porcentaje_tarjeta": 15, "total_redondeo": 1},
{"producto": "TELGOPOR", "modelo": "TELGOPOR", "ancho": "1.20", "alto": "2.40", "tipo": "Estándar", "placas_por_metro": 1, "stock": 0, "costo": null, "porcentaje_ganancia": 100, "porcentaje_tarjeta": 15, "total_redondeo": 1},
{"producto": "PLACAS", "modelo": "QUEBRACHO", "ancho": "1.20", "alto": "2.40", "tipo": "Estándar", "placas_por_metro": 7, "stock": 0, "costo": null, "porcentaje_ganancia": 100, "porcentaje_tarjeta": 15, "total_redondeo": 1},
{"producto": "PVC_PERFIL", "modelo": "F CEDRO 5M", "ancho": "1.20", "alto": "2.40", "tipo": "Estándar", "placas_por_metro": 1, "stock": 0, "costo": null, "porcentaje_ganancia": 100, "porcentaje_tarjeta": 15, "total_redondeo": 1},
{"producto": "SIMIL_MARMOL", "modelo": "MARQUINA BRILLANTE 2,4M", "ancho": "1.20", "alto": "2.40", "tipo": "Estándar", "placas_por_metro": 1, "stock": 0, "costo": null, "porcentaje_ganancia": 100, "porcentaje_tarjeta": 15, "total_redondeo": 1},
{"producto": "PERFIL_GALVANIZADO", "modelo": "SOLERA 35mm", "ancho": "1.20", "alto": "2.40", "tipo": "Estándar", "placas_por_metro": 1, "stock": 0, "costo": null, "porcentaje_ganancia": 100, "porcentaje_tarjeta": 15, "total_redondeo": 1},
{"producto": "PERFIL_GALVANIZADO", "modelo": "MONTANTE 35mm", "ancho": "1.20", "alto": "2.40", "tipo": "Estándar", "placas_por_metro": 1, "stock": 0, "costo": null, "porcentaje_ganancia": 100, "porcentaje_tarjeta": 15, "total_redondeo": 1},
{"producto": "PERFIL_GALVANIZADO", "modelo": "SOLERA 70nm", "ancho": "1.20", "alto": "2.40", "tipo": "Estándar", "placas_por_metro": 1, "stock": 0, "costo": null, "porcentaje_ganancia": 100, "porcentaje_tarjeta": 15, "total_redondeo": 1},
{"producto": "PERFIL_GALVANIZADO", "modelo": "MONTANTE 70mm", "ancho": "1.20", "alto": "2.40", "tipo": "Estándar", "placas_por_metro": 1, "stock": 0, "costo": null, "porcentaje_ganancia": 100, "porcentaje_tarjeta": 15, "total_redondeo": 1},
{"producto": "MATERIAL", "modelo": "TORNILLO T1", "ancho": "1.20", "alto": "2.40", "tipo": "Estándar", "placas_por_metro": 1, "stock": 0, "costo": null, "porcentaje_ganancia": 100, "porcentaje_tarjeta": 15, "total_redondeo": 1},
{"producto": "MATERIAL", "modelo": "TORNILLOS T2", "ancho": "1.20", "alto": "2.40", "tipo": "Estándar", "placas_por_metro": 1, "stock": 0, "costo": null, "porcentaje_ganancia": 100, "porcentaje_tarjeta": 15, "total_redondeo": 1},
{"producto": "MATERIAL", "modelo": "FIJACIÓN N°8", "ancho": "1.20", "alto": "2.40", "tipo": "Estándar", "placas_por_metro": 1, "stock": 0, "costo": null, "porcentaje_ganancia": 100, "porcentaje_tarjeta": 15, "total_redondeo": 1},
{"producto": "SIMIL_MARMOL", "modelo": "TERMINACION_DORADA", "ancho": "1.20", "alto": "2.40", "tipo": "Estándar", "placas_por_metro": 1, "stock": 0, "costo": null, "porcentaje_ganancia": 100, "porcentaje_tarjeta": 15, "total_redondeo": 1},
{"producto": "SIMIL_MARMOL", "modelo": "TERMINACION_NEGRA", "ancho": "1.20", "alto": "2.40", "tipo": "Estándar", "placas_por_metro": 1, "stock": 0, "costo": null, "porcentaje_ganancia": 100, "porcentaje_tarjeta": 15, "total_redondeo": 1},
{"producto": "SIMIL_MARMOL", "modelo": "TERMINACION_PLATEADA", "ancho": "1.20", "alto": "2.40", "tipo": "Estándar", "placas_por_metro": 1, "stock": 0, "costo": null, "porcentaje_ganancia": 100, "porcentaje_tarjeta": 15, "total_redondeo": 1},
{"producto": "WPC_EXTERIOR", "modelo": "D.COFFE 2,9M", "ancho": "1.20", "alto": "2.40", "tipo": "Estándar", "placas_por_metro": 1, "stock": 0, "costo": null, "porcentaje_ganancia": 100, "porcentaje_tarjeta": 15, "total_redondeo": 1},
{"producto": "WPC_EXTERIOR", "modelo": "LINO 2,9M", "ancho": "1.20", "alto": "2.40", "tipo": "Estándar", "placas_por_metro": 1, "stock": 0, "costo": null, "porcentaje_ganancia": 100, "porcentaje_tarjeta": 15, "total_redondeo": 1},
{"producto": "WPC_EXTERIOR", "modelo": "LADRILLO 2,9M", "ancho": "1.20", "alto": "2.40", "tipo": "Estándar", "placas_por_metro": 1, "stock": 0, "costo": null, "porcentaje_ganancia": 100, "porcentaje_tarjeta": 15, "total_redondeo": 1},
{"producto": "WPC_EXTERIOR", "modelo": "L.COFFE 2,9M", "ancho": "1.20", "alto": "2.40", "tipo": "Estándar", "placas_por_metro": 1, "stock": 0, "costo": null, "porcentaje_ganancia": 100, "porcentaje_tarjeta": 15, "total_redondeo": 1},
{"producto": "WPC_EXTERIOR", "modelo": "BASALTO", "ancho": "1.20", "alto": "2.40", "tipo": "Estándar", "placas_por_metro": 1, "stock": 0, "costo": null, "porcentaje_ganancia": 100, "porcentaje_tarjeta": 15, "total_redondeo": 1},
{"producto": "WPC", "modelo": "ROBLE C 2,7M", "ancho": "1.20", "alto": "2.40", "tipo": "Estándar", "placas_por_metro": 1, "stock": 0, "costo": null, "porcentaje_ganancia": 100, "porcentaje_tarjeta": 15, "total_redondeo": 1},
{"producto": "MATERIAL", "modelo": "CUTTER", "ancho": "1.20", "alto": "2.40", "tipo": "Estándar", "placas_por_metro": 1, "stock": 0, "costo": null, "porcentaje_ganancia": 100, "porcentaje_tarjeta": 15, "total_redondeo": 1},
{"producto": "MATERIAL", "modelo": "PISTOLA", "ancho": "1.20", "alto": "2.40", "tipo": "Estándar", "placas_por_metro": 1, "stock": 0, "costo": null, "porcentaje_ganancia": 100, "porcentaje_tarjeta": 15, "total_redondeo": 1},
{"producto": "SIMIL_MARMOL", "modelo": "Blanco con dorado 3mm", "ancho": "1.20", "alto": "2.40", "tipo": "Estándar", "placas_por_metro": 1, "stock": 0, "costo": null, "porcentaje_ganancia": 100, "porcentaje_tarjeta": 15, "total_redondeo": 1},
{"producto": "SIMIL_MARMOL", "modelo": "Negro brillante 3mm", "ancho": "1.20", "alto": "2.40", "tipo": "Estándar", "placas_por_metro": 1, "stock": 0, "costo": null, "porcentaje_ganancia": 100, "porcentaje_tarjeta": 15, "total_redondeo": 1},
{"producto": "SIMIL_MARMOL", "modelo": "Gris veteado 3mm", "ancho": "1.20", "alto": "2.40", "tipo": "Estándar", "placas_por_metro": 1, "stock": 0, "costo": null, "porcentaje_ganancia": 100, "porcentaje_tarjeta": 15, "total_redondeo": 1},
{"producto": "SIMIL_MARMOL", "modelo": "Espejada gris 5mm", "ancho": "1.20", "alto": "2.40", "tipo": "Estándar", "placas_por_metro": 1, "stock": 0, "costo": null, "porcentaje_ganancia": 100, "porcentaje_tarjeta": 15, "total_redondeo": 1},
{"producto": "SIMIL_MARMOL", "modelo": "Espejada dorado 5 mm", "ancho": "1.20", "alto": "2.40", "tipo": "Estándar", "placas_por_metro": 1, "stock": 0, "costo": null, "porcentaje_ganancia": 100, "porcentaje_tarjeta": 15, "total_redondeo": 1},
{"producto": "SIMIL_MARMOL", "modelo": "Espejada negra 5mm", "ancho": "1.20", "alto": "2.40", "tipo": "Estándar", "placas_por_metro": 1, "stock": 0, "costo": null, "porcentaje_ganancia": 100, "porcentaje_tarjeta": 15, "total_redondeo": 1},